<?xml version="1.0"?>
<!DOCTYPE hibernate-mapping PUBLIC "-//Hibernate/Hibernate Mapping DTD 3.0//EN"
"http://www.hibernate.org/dtd/hibernate-mapping-3.0.dtd">
<!-- Generated 02/02/2014 11:46:25 AM by Hibernate Tools 4.0.0 -->
<hibernate-mapping>
	<class name="dev.com.matricula.model.Parentesco" table="parentesco"
		catalog="bdmatricula">
		<composite-id name="id" class="dev.com.matricula.model.ParentescoId">
			<key-property name="parentesco" type="string">
				<column name="Parentesco" length="15" />
			</key-property>
			<key-property name="idApoderado" type="string">
				<column name="IdApoderado" length="8" />
			</key-property>
			<key-property name="idAlumno" type="string">
				<column name="IdAlumno" length="5" />
			</key-property>
			<key-property name="codUsuario" type="java.lang.Integer">
				<column name="CodUsuario" />
			</key-property>
			<key-property name="fechaOperacion" type="timestamp">
				<column name="FechaOperacion" length="19" />
			</key-property>
		</composite-id>
		<many-to-one name="alumno" class="dev.com.matricula.model.Alumno"
			update="false" insert="false" fetch="select">
			<column name="IdAlumno" length="5" not-null="true" />
		</many-to-one>
		<many-to-one name="apoderado" class="dev.com.matricula.model.Apoderado"
			update="false" insert="false" fetch="select">
			<column name="IdApoderado" length="8" not-null="true" />
		</many-to-one>
	</class>
</hibernate-mapping>
